{
  "Camp": "重桜",
  "History": "計画1896年度\n起工1898年1月\n進水1899年3月15日\n就役1899年5月13日\nその後1905年12月12日駆逐艦に種別変更\n1912年8月28日三等駆逐艦\n1922年4月1日特務艇編入、二等掃海艇類別\n1923年6月30日二等掃海特務艇に類別変更\n1923年8月1日雑役船編入、運貨船指定、公称第2526号に改称\n除籍1923年8月1日\n",
  "Description": "不知火（しらぬい / しらぬひ）は、大日本帝国海軍の駆逐艦で、東雲型駆逐艦の4番艦である。同名艦に陽炎型駆逐艦の「不知火 不知火」があるため、こちらは「不知火 (初代)」や「不知火I」などと表記される。\n\n1899年5月13日、イギリス・ジョン・アイ・ソーニクロフト・アンド・カンパニー・リミッテッドソーニクロフト社で竣工し、水雷艇（駆逐艇）に類別。同年11月10日、横須賀に到着。1900年6月22日、軍艦に編入され、駆逐艦に類別。\n\n1904年、日露戦争が勃発した際には第二艦隊 第2艦隊第5駆逐隊に所属していた<ref namergm>『聯合艦隊軍艦銘銘伝』普及版、406頁。</ref>。旅順口攻撃、黄海海戦 黄海海戦、日本海海戦、樺太の戦い 樺太の戦いなどに参加した<ref namergm/>。\n\n1922年4月1日、特務艇（二等掃海艇）に編入。1923年6月30日、二等掃海特務艇に類別変更。同年8月1日、雑役船（運貨船）に編入され、公称第2625号に改称。1925年2月25日、廃船認許。\nhttps://ja.wikipedia.org/wiki/%E4%B8%8D%E7%9F%A5%E7%81%AB_(%E9%99%BD%E7%82%8E%E5%9E%8B%E9%A7%86%E9%80%90%E8%89%A6)",
  "Name": "不知火",
  "Type": "Destroyer"
}